pyppluss/__init__.py
pyppluss/base_functions.py
pyppluss/fastqs.py
pyppluss/polygon_plus_segments.py
pyppluss/segment_models.py
pyppluss-0.1.5.3.dist-info/LICENSE
pyppluss-0.1.5.3.dist-info/METADATA
pyppluss-0.1.5.3.dist-info/WHEEL
pyppluss-0.1.5.3.dist-info/top_level.txt
pyppluss-0.1.5.3.dist-info/RECORD
