Metadata-Version: 2.1
Name: pyppluss
Version: 0.1.5.3
Summary: Models for transiting exoplanets with rings
Home-page: https://github.com/EdanRein/pyPplusS
Author: Edan Rein
Author-email: edanrein2000@gmail.com
License: MIT
Platform: UNKNOWN
Classifier: Programming Language :: Python :: 3
Classifier: License :: OSI Approved :: MIT License
Classifier: Operating System :: OS Independent
Classifier: Development Status :: 5 - Production/Stable
License-File: LICENSE
Requires-Dist: numpy
Requires-Dist: scipy
